Flask_Sphinx_Themes-1.0.2.dist-info/DESCRIPTION.rst
Flask_Sphinx_Themes-1.0.2.dist-info/LICENSE.txt
Flask_Sphinx_Themes-1.0.2.dist-info/METADATA
Flask_Sphinx_Themes-1.0.2.dist-info/RECORD
Flask_Sphinx_Themes-1.0.2.dist-info/WHEEL
Flask_Sphinx_Themes-1.0.2.dist-info/entry_points.txt
Flask_Sphinx_Themes-1.0.2.dist-info/metadata.json
Flask_Sphinx_Themes-1.0.2.dist-info/top_level.txt
flask_sphinx_themes/__init__.py
flask_sphinx_themes/pygments.py
flask_sphinx_themes/flask/layout.html
flask_sphinx_themes/flask/relations.html
flask_sphinx_themes/flask/theme.conf
flask_sphinx_themes/flask/static/flasky.css_t
flask_sphinx_themes/flask_small/layout.html
flask_sphinx_themes/flask_small/theme.conf
flask_sphinx_themes/flask_small/static/flasky.css_t
